paperplots/__init__.py
paperplots/paperplots.py
paperplots-0.2.0.dist-info/LICENSE
paperplots-0.2.0.dist-info/METADATA
paperplots-0.2.0.dist-info/WHEEL
paperplots-0.2.0.dist-info/top_level.txt
paperplots-0.2.0.dist-info/RECORD
